{"oras":[
	{"id":"task1",
		"task":"Complete the OR / AS Hoenn Pokedex (211)",
		"category":"catchemall",
		"markTask":false,
		"row": 3,
		"col": 1,
		"splitCol":2,
		"subtasks":[
			{"id":"sub1", "task":"Obtain 'Platinum Crowns' on All Routes"},
			{"id":"sub2", "task":"Capture Groudon / Kyogre (Cave of Origin)", "formats":[{"word":"Groudon","format":"ruby"},{"word":"Kyogre","format":"sapphire"}]},
			{"id":"sub3", "task":"Trade for Kyogre / Groudon", "formats":[{"word":"Groudon","format":"sapphire"},{"word":"Kyogre","format":"ruby"}]},
			{"id":"sub4", "task":"Capture Regirock (Desert Ruins)", "tooltip":"Available at different times"},
			{"id":"sub5", "task":"Capture Regice (Island Cave)", "tooltip":"Available at different times"},
			{"id":"sub6", "task":"Capture Registeel (Ancient Tomb)", "tooltip":"Available at different times"},
			{"id":"sub7", "task":"Capture Rayquaza (Sky Pillar)"},
			{"id":"sub8", "task":"Capture Deoxys (Sky Pillar)"},
			{"id":"sub9", "task":"Trade for Latias / Latios (OR EON Ticket)","formats":[{"word":"Latias","format":"ruby"},{"word":"Latios","format":"sapphire"}]}
		]
	},
	{"id":"task2",
		"task":"Capture Additional In-Game Legendaries",
		"category":"legendary",
		"row": 3,
		"col": 3,
		"sort":"alpha",
		"splitCol":3,
		"subtasks":[
			{"id":"sub1", "task":"Capture Regigigas (Island Cave)", "tooltip":"Available at different times"},
			{"id":"sub2", "task":"Capture Ho-oh / Lugia (Sea Mauville)"},
			{"id":"sub3", "task":"Capture Heatran (Scorched Slab)"},
			{"id":"sub4", "task":"Capture Uxie (Nameless Cavern)", "tooltip":"Available at different times"},
			{"id":"sub5", "task":"Capture Mesprit (Nameless Cavern)", "tooltip":"Available at different times"},
			{"id":"sub6", "task":"Capture Azelf (Nameless Cavern)", "tooltip":"Available at different times"},
			{"id":"sub7", "task":"Capture Palkia / Dialgia (Mirage in Sky)", "tooltip":"Have Uxie, Mesprit, & Azelf on your team"},
			{"id":"sub8", "task":"Capture Giratina (Mirage in Sky)", "tooltip":"Have Palkia & Dialga on your team"},
			{"id":"sub9", "task":"Capture Virizion (Pathless Plain)", "tooltip":"You need 3 PKMN with max effort values on your team. Available on different days."},
			{"id":"sub10", "task":"Capture Terrakion (Pathless Plain)", "tooltip":"You need 3 PKMN with max effort values on your team. Available on different days."},
			{"id":"sub11", "task":"Capture Cobalion (Pathless Plain)", "tooltip":"You need 3 PKMN with max effort values on your team. Available on different days."},
			{"id":"sub12", "task":"Capture Reshiram / Zekrom (Fabled Cave)", "tooltip":"Have a Lvl 100 PKMN on your team"},
			{"id":"sub13", "task":"Capture Kyurem (Gnarled Den)", "tooltip":"Have Reshiram & Zekrom on your team"},
			{"id":"sub14", "task":"Capture Raikou (Trackless Forest)", "tooltip":"Have Ho-oh or Lugia on your team"},
			{"id":"sub15", "task":"Capture Entei (Trackless Forest)", "tooltip":"Have Ho-oh or Lugia on your team"},
			{"id":"sub16", "task":"Capture Suicune (Trackless Forest)", "tooltip":"Have Ho-oh or Lugia on your team"},
			{"id":"sub17", "task":"Capture Tornadus / Thundurus", "tooltip":"Mirage spot in the sky with castform on your team"},
			{"id":"sub18", "task":"Capture Landorus (Mirage in Sky)", "tooltip":"Have Tornadus & Thundurus on your team"},
			{"id":"sub20", "task":"Capture Cresselia (Cressent Isle)"}
		]
	},
	{"id":"task3",
		"task":"Complete National Dex (719)",
		"category":"catchemall",
		"markTask":false,
		"row": 3,
		"col": 2,
		"subtasks":[
			{"id":"sub1", "task":"Obtain Johto Starter From Prof. Birch"},
			{"id":"sub2", "task":"Obtain Unova Starter From Prof. Birch"},
			{"id":"sub3", "task":"Obtain Sinnoh Starter From Prof. Birch"}
		]
	},
	{"id":"task4",
		"task":"Collect All \"New\" Mega Stones",
		"category":"megastones",
		"row": 3,
		"col": 12,
		"sort":"alpha",
		"splitCol":2,
		"subtasks":[
			{"id":"sub1", "task":"Beedrill", "spoiler":"(Sea Mauville)", "tooltip":"From Beginning"},
			{"id":"sub2", "task":"Pidgeot", "spoiler":"(Rustboro - Show Mr. Stone the Intriguing Stone)", "tooltip":"From Beginning"},
			{"id":"sub3", "task":"Slowbro", "spoiler":"(Shoal Cave - Give man 4 Shoal Salts & 4 Shoal Shells)", "tooltip":"From Beginning"},
			{"id":"sub4", "task":"Steelix", "spoiler":"(Granite Cave)", "tooltip":"From Beginning"},
			{"id":"sub5", "task":"Steelix", "spoiler":"(Transfer from Demo Version)", "formats":[{"all":"seafoam"}]},
			{"id":"sub6", "task":"Sceptile", "spoiler":"(Route 120 (If Starter), Route 114 - Stone Salesman (If not Starter))"},
			{"id":"sub7", "task":"Swampert", "spoiler":"(Route 120 (If Starter), Route 114 - Stone Salesman (If not Starter))"},
			{"id":"sub8", "task":"Sableye", "spoiler":"(Sootopolis City)", "tooltip":"From Beginning"},
			{"id":"sub9", "task":"Sharpedo", "spoiler":"(Battle Resort (Omega Ruby) / Aqua Hideout - Delta Ep(Alpha Sapphire))"},
			{"id":"sub10", "task":"Camerupt", "spoiler":"(Magma Hideout - Delta Ep (Omega Ruby) / Battle Resort (Alpha Sapphire))"},
			{"id":"sub11", "task":"Altaria", "spoiler":"(Lilycove City - Show Collector Altaria)", "tooltip":"From Beginning"},
			{"id":"sub12", "task":"Glalie", "spoiler":"(Shoal Cave Basement)", "tooltip":"From Beginning"},
			{"id":"sub13", "task":"Glalie", "spoiler":"(Transfer from Demo Version)", "formats":[{"all":"seafoam"}]},
			{"id":"sub14", "task":"Salamence", "spoiler":"(Meteor Falls - Zinnia's Grandmother)", "tooltip":"After Delta Episode"},
			{"id":"sub15", "task":"Metagross", "spoiler":"(Pokemon League - Steven Stone Rematch)", "tooltip":"After Delta Episode"},
			{"id":"sub16", "task":"Metagross", "spoiler":"(Shiny Beldum Event)", "formats":[{"all":"seafoam"}]},
			{"id":"sub17", "task":"Latias", "spoiler":"(Littleroot Town - Mother / On Latias (Alpha Sapphire)"},
			{"id":"sub18", "task":"Latios", "spoiler":"(On Latios (Omega Ruby)/ Littleroot Town - Mother)"},
			{"id":"sub19", "task":"Lopunny", "spoiler":"(Mauville Hills - Man in suit)", "tooltip":"After Primal Groudon/Kyogre narrative"},
			{"id":"sub20", "task":"Gallade", "spoiler":"(Professor Cozmo)", "tooltip":"After Delta Episode"},
			{"id":"sub21", "task":"Audino", "spoiler":"(Battle Resort - Looker)", "tooltip":"After Delta Episode"},
			{"id":"sub22", "task":"Diancie", "spoiler":"(Diancie Event - Stone from Pokemon Center)", "formats":[{"all":"seafoam"}]}
		]
	},
	{"id":"task5",
		"task":"Complete All Master Rank Pokemon Contests",
		"category":"activities",
		"row": 3,
		"col": 18,
		"subtasks":[]
	},
	{"id":"task6",
		"task":"Obtain Both Bicycles (Acro & Mach Bikes)",
		"category":"activities",
		"markTask":false,
		"row": 3,
		"col": 17,
		"subtasks":[
			{"id":"sub1", "task":"Show Mach bike to Hex Maniac (Route 111)"},
			{"id":"sub2", "task":"Show Acro bike to Bird Keeper (Route 119)"},
			{"id":"sub3", "task":"Show either bike to triathelete (Battle Resort)"}
		]
	},
	{"id":"task7",
		"task":"Collect All 100 Technical Machines (TMs)",
		"category":"tms",
		"row": 8,
		"col": 8,
		"splitCol": 4,
		"sort":"alpha",
		"subtasks":[
			{"id":"sub1", "task":"Hone Claws"},
			{"id":"sub2", "task":"Dragon Claw"},
			{"id":"sub3", "task":"Psyshock"},
			{"id":"sub4", "task":"Calm Mind"},
			{"id":"sub5", "task":"Roar"},
			{"id":"sub6", "task":"Toxic"},
			{"id":"sub7", "task":"Hail"},
			{"id":"sub8", "task":"Bulk up"},
			{"id":"sub9", "task":"Venoshock"},
			{"id":"sub10", "task":"Hidden Power"},
			{"id":"sub11", "task":"Sunny Day"},
			{"id":"sub12", "task":"Taunt"},
			{"id":"sub13", "task":"Ice Beam"},
			{"id":"sub14", "task":"Blizzard"},
			{"id":"sub15", "task":"Hyper Beam"},
			{"id":"sub16", "task":"Light Screen"},
			{"id":"sub17", "task":"Protect"},
			{"id":"sub18", "task":"Rain Dance"},
			{"id":"sub19", "task":"Roost"},
			{"id":"sub20", "task":"Safeguard"},
			{"id":"sub21", "task":"Frustration"},
			{"id":"sub22", "task":"Solar Beam"},
			{"id":"sub23", "task":"Smack Down"},
			{"id":"sub24", "task":"Thunderbolt"},
			{"id":"sub25", "task":"Thunder"},
			{"id":"sub26", "task":"Earthquake"},
			{"id":"sub27", "task":"Return"},
			{"id":"sub28", "task":"Dig"},
			{"id":"sub29", "task":"Psychic"},
			{"id":"sub30", "task":"Shadow Ball"},
			{"id":"sub31", "task":"Brick Break"},
			{"id":"sub32", "task":"Double Team"},
			{"id":"sub33", "task":"Reflect"},
			{"id":"sub34", "task":"Sludge Wave"},
			{"id":"sub35", "task":"Flamethrower"},
			{"id":"sub36", "task":"Sludge Bomb"},
			{"id":"sub37", "task":"Sandstorm"},
			{"id":"sub38", "task":"Fire Blast"},
			{"id":"sub39", "task":"Rock Tomb"},
			{"id":"sub40", "task":"Aerial Ace"},
			{"id":"sub41", "task":"Torment"},
			{"id":"sub42", "task":"Facade"},
			{"id":"sub43", "task":"Flame Charge"},
			{"id":"sub44", "task":"Rest"},
			{"id":"sub45", "task":"Attract"},
			{"id":"sub46", "task":"Thief"},
			{"id":"sub47", "task":"Low Sweep"},
			{"id":"sub48", "task":"Round"},
			{"id":"sub49", "task":"Echoed Voice"},
			{"id":"sub50", "task":"Overheat"},
			{"id":"sub51", "task":"Steel Wing"},
			{"id":"sub52", "task":"Focus Blast"},
			{"id":"sub53", "task":"Energy Ball"},
			{"id":"sub54", "task":"False Swipe"},
			{"id":"sub55", "task":"Scald"},
			{"id":"sub56", "task":"Fling"},
			{"id":"sub57", "task":"Charge Beam"},
			{"id":"sub58", "task":"Sky Drop"},
			{"id":"sub59", "task":"Incinerate"},
			{"id":"sub60", "task":"Quash"},
			{"id":"sub61", "task":"Will-o-wisp"},
			{"id":"sub62", "task":"Acrobatics"},
			{"id":"sub63", "task":"Embargo"},
			{"id":"sub64", "task":"Explosion"},
			{"id":"sub65", "task":"Shadow Claw"},
			{"id":"sub66", "task":"Payback"},
			{"id":"sub67", "task":"Retaliate"},
			{"id":"sub68", "task":"Giga Impact"},
			{"id":"sub69", "task":"Rock Polish"},
			{"id":"sub70", "task":"Flash"},
			{"id":"sub71", "task":"Stone Edge"},
			{"id":"sub72", "task":"Volt Switch"},
			{"id":"sub73", "task":"Thunder Wave"},
			{"id":"sub74", "task":"Gyro Ball"},
			{"id":"sub75", "task":"Swords Dance"},
			{"id":"sub76", "task":"Struggle Bug"},
			{"id":"sub77", "task":"Psych up"},
			{"id":"sub78", "task":"Bulldoze"},
			{"id":"sub79", "task":"Frost Breath"},
			{"id":"sub80", "task":"Rock Slide"},
			{"id":"sub81", "task":"X-Scissor"},
			{"id":"sub82", "task":"Dragon Tail"},
			{"id":"sub83", "task":"Infestation"},
			{"id":"sub84", "task":"Poison Jab"},
			{"id":"sub85", "task":"Dream Eater"},
			{"id":"sub86", "task":"Grass Knot"},
			{"id":"sub87", "task":"Swagger"},
			{"id":"sub88", "task":"Sleep Talk"},
			{"id":"sub89", "task":"U-Turn"},
			{"id":"sub90", "task":"Substitute"},
			{"id":"sub91", "task":"Flash Cannon"},
			{"id":"sub92", "task":"Trick Room"},
			{"id":"sub93", "task":"Wild Charge"},
			{"id":"sub94", "task":"Secret Power"},
			{"id":"sub95", "task":"Snarl"},
			{"id":"sub96", "task":"Nature Power"},
			{"id":"sub97", "task":"Dark Pulse"},
			{"id":"sub98", "task":"Power-up Punch"},
			{"id":"sub99", "task":"Dazzling Gleam"},
			{"id":"sub100", "task":"Confide"}
		]
	},
	{"id":"task8",
		"task":"Berry Checklist",
		"category":"berry",
		"row": 9,
		"col": 9,
		"splitCol": 4,
		"sort":"alpha",
		"subtasks":[
			{"id":"sub1", "task":"Cherri"},
			{"id":"sub2", "task":"Leppa"},
			{"id":"sub3", "task":"Figgy"},
			{"id":"sub4", "task":"Razz"},
			{"id":"sub5", "task":"Pomeg"},
			{"id":"sub6", "task":"Tamato"},
			{"id":"sub7", "task":"Occa"},
			{"id":"sub8", "task":"Chople"},
			{"id":"sub9", "task":"Payapa"},
			{"id":"sub10", "task":"Haban"},
			{"id":"sub11", "task":"Custap"},
			{"id":"sub12", "task":"Roseli"},
			{"id":"sub13", "task":"Chesto"},
			{"id":"sub14", "task":"Oran"},
			{"id":"sub15", "task":"Wiki"},
			{"id":"sub16", "task":"Bluk"},
			{"id":"sub17", "task":"Kelpsy"},
			{"id":"sub18", "task":"Cornn"},
			{"id":"sub19", "task":"Pamrre"},
			{"id":"sub20", "task":"Belue"},
			{"id":"sub21", "task":"Passho"},
			{"id":"sub22", "task":"Yache"},
			{"id":"sub23", "task":"Coba"},
			{"id":"sub24", "task":"Ganlon"},
			{"id":"sub25", "task":"Apicot"},
			{"id":"sub26", "task":"Rowap"},
			{"id":"sub27", "task":"Pecha"},
			{"id":"sub28", "task":"Persim"},
			{"id":"sub29", "task":"Mago"},
			{"id":"sub30", "task":"Nanab"},
			{"id":"sub31", "task":"Qualot"},
			{"id":"sub32", "task":"Magost"},
			{"id":"sub33", "task":"Spelon"},
			{"id":"sub34", "task":"Kasib"},
			{"id":"sub35", "task":"Colbur"},
			{"id":"sub36", "task":"Petaya"},
			{"id":"sub37", "task":"Lansat"},
			{"id":"sub38", "task":"Kee"},
			{"id":"sub39", "task":"Rawst"},
			{"id":"sub40", "task":"Lum"},
			{"id":"sub41", "task":"Aguav"},
			{"id":"sub42", "task":"Wepear"},
			{"id":"sub43", "task":"Hondew"},
			{"id":"sub44", "task":"Rabuta"},
			{"id":"sub45", "task":"Watmel"},
			{"id":"sub46", "task":"Durin"},
			{"id":"sub47", "task":"Rindo"},
			{"id":"sub48", "task":"Kebia"},
			{"id":"sub49", "task":"Tanga"},
			{"id":"sub50", "task":"Babiri"},
			{"id":"sub51", "task":"Salac"},
			{"id":"sub52", "task":"Starf"},
			{"id":"sub53", "task":"Aspear"},
			{"id":"sub54", "task":"Sitrus"},
			{"id":"sub55", "task":"Iapapa"},
			{"id":"sub56", "task":"Pinap"},
			{"id":"sub57", "task":"Grepa"},
			{"id":"sub58", "task":"Nomel"},
			{"id":"sub59", "task":"Wacan"},
			{"id":"sub60", "task":"Shuca"},
			{"id":"sub61", "task":"Charti"},
			{"id":"sub62", "task":"Chilan"},
			{"id":"sub63", "task":"Liechi"},
			{"id":"sub64", "task":"Enigma"},
			{"id":"sub65", "task":"Jaboca"},
			{"id":"sub66", "task":"Maranga"}
		]
	},
	{"id":"task9",
		"task":"Complete the Delta Episode Sub-Plot",
		"category":"epilogue",
		"row": 3,
		"col": 15,
		"splitCol":2,
		"subtasks":[
			{"id":"sub1", "task":"1. Encounter Zinnia In Littleroot"},
			{"id":"sub2", "task":"2. Defeat Courtney / Matt in Petalburg","formats":[{"word":"Courtney","format":"ruby"},{"word":"Matt","format":"sapphire"}]},
			{"id":"sub3", "task":"3. Talk to Mr. Stone in Rustboro"},
			{"id":"sub4", "task":"4. Defeat Zinnia in Granite Cave"},
			{"id":"sub5", "task":"5. Talk with Prof. Cozmo in Mossdeep"},
			{"id":"sub6", "task":"6. Talk to Steven at Meteor Falls"},
			{"id":"sub7", "task":"7. Help Devon Corp in Rustboro"},
			{"id":"sub8", "task":"8. Defeat Courtney / Matt in Mossdeep","formats":[{"word":"Courtney","format":"ruby"},{"word":"Matt","format":"sapphire"}]},
			{"id":"sub9", "task":"9. Defeat Team Magma / Team Aqua Hideout","formats":[{"word":"Team Magma","format":"ruby"},{"word":"Team Aqua","format":"sapphire"}]},
			{"id":"sub10", "task":"10. Talk to Steven in Mossdeep"},
			{"id":"sub11", "task":"11. Talk to Wallace in Sootopolis & Defeat Him at Entrance of Sky Pillar"},
			{"id":"sub12", "task":"12. Talk to Zinnia at Base of Sky Pillar"},
			{"id":"sub13", "task":"13. Capture Rayquaza & Battle Zinnia at Sky Pillar Summit"},
			{"id":"sub14", "task":"14. Fly to Space and Capture Deoxys"},
			{"id":"sub15", "task":"15. Watch the Meteor Shower with May / Brendan at Mossdeep"}
		]
	},
	{"id":"task10",
		"task":"Complete Regular & Super Battle Maison Battles",
		"category":"battle",
		"row": 3,
		"col": 13,
		"splitCol":2,
		"subtasks":[
			{"id":"sub1", "task":"Single Battle", "multicheck":2},
			{"id":"sub2", "task":"Double Battle", "multicheck":2},
			{"id":"sub3", "task":"Triple Battle", "multicheck":2},
			{"id":"sub4", "task":"Rotation Battle", "multicheck":2},
			{"id":"sub5", "task":"Multi Battle", "multicheck":2}
		]
	},
	{"id":"task11",
		"task":"Rematch \"Mega\" Elite Four Post-Delta Episode",
		"category":"battle",
		"row": 3,
		"col": 14
	},
	{"id":"task12",
		"task":"Rematch Wally at the Battle Resort",
		"category":"battle",
		"row": 3,
		"col": 14,
		"subtasks":[
			{"id":"sub1", "task":"Rematch Wally After Beating Super Battle"}
		]
	},
	{"id":"task13",
		"task":"Complete All Mauville Food Court Battles",
		"category":"battle",
		"row": 3,
		"col": 14,
		"subtasks":[
			{"id":"sub1", "task":"Village Sub Combo (Single)"},
			{"id":"sub2", "task":"Magnemite Croquette (Double)"},
			{"id":"sub3", "task":"Mauville Ramen Bowl (Triple)"}
		]
	},
	{"id":"task14",
		"task":"Obtain Gold Trainer Card",
		"category":"upgrades",
		"row": 3,
		"col": 5,
		"subtasks":[
			{"id":"sub1", "task":"Defeat the Elite Four", "default":"true"},
			{"id":"sub2", "task":"Complete the Hoenn Dex"},
			{"id":"sub3", "task":"Defeat 1 Battle Maison 50th Streak"}
		]
	},
	{"id":"task16",
		"task":"Collect All \"Retro\" Mega Stones",
		"category":"megastones",
		"row": 3,
		"col": 12,
		"sort":"alpha",
		"splitCol":2,
		"subtasks":[
			{"id":"sub1","task":"Venusaur", "spoiler":"(Route 119)", "tooltip":"After Primal Groudon/Kyogre narrative"},
			{"id":"sub2","task":"Charizard X", "spoiler":"(Fiery Path)", "tooltip":"After Primal Groudon/Kyogre narrative"},
			{"id":"sub3","task":"Charizard Y", "spoiler":"(Scorched Slab)", "tooltip":"After Primal Groudon/Kyogre narrative"},
			{"id":"sub4","task": "Blastoise", "spoiler":"(SS Tidal)", "tooltip":"From Delta Episode"},
			{"id":"sub5","task":"Alakazam", "spoiler":"(Slateport City Market)", "tooltip":"From Beginning"},
			{"id":"sub6","task":"Gengar", "spoiler":"(Battle Resort)", "tooltip":"After Delta Episode"},
			{"id":"sub7","task":"Kangaskhan", "spoiler":"(Pacifidlog Town)", "tooltip":"After Primal Groudon/Kyogre narrative"},
			{"id":"sub8","task":"Pinsir", "spoiler":"(Route 124)", "tooltip":"From Beginning"},
			{"id":"sub9","task":"Gyarados", "spoiler":"(Route 123 - In mouth of Poochyena)", "tooltip":"From Beginning"},
			{"id":"sub10","task":"Aerodactyl", "spoiler":"(Meteor Falls)", "tooltip":"After Primal Groudon/Kyogre narrative"},
			{"id":"sub11","task":"Mewtwo X", "spoiler":"(Littleroot Town)", "tooltip":"After Primal Groudon/Kyogre narrative"},
			{"id":"sub12","task":"Mewtwo Y", "spoiler":"(Pokemon League)", "tooltip":"After Primal Groudon/Kyogre narrative"},
			{"id":"sub13","task":"Ampharos", "spoiler":"(New Mauville)", "tooltip":"After Primal Groudon/Kyogre narrative"},
			{"id":"sub14","task":"Scizor", "spoiler":"(Petalburg Woods)", "tooltip":"After Primal Groudon/Kyogre narrative"},
			{"id":"sub15","task":"Heracross", "spoiler":"(Route 127)", "tooltip":"From Beginning"},
			{"id":"sub16","task":"Houndoom", "spoiler":"(Lavaridge Town)", "tooltip":"After Primal Groudon/Kyogre narrative"},
			{"id":"sub17","task":"Tyranitar", "spoiler":"(Jagged Pass)", "tooltip":"After Primal Groudon/Kyogre narrative"},
			{"id":"sub18","task":"Blaziken", "spoiler":"(Route 120 (If Starter), Route 114 Stone Salesman (If not Starter))"},
			{"id":"sub19","task":"Gardevoir", "spoiler":"(Verdanturf Town - From Wanda)", "tooltip":"After Primal Groudon/Kyogre narrative"},
			{"id":"sub20","task":"Mawile", "spoiler":"(Verdanturf Town)", "tooltip":"From Beginning"},
			{"id":"sub21","task":"Aggron", "spoiler":"(Rusturf Tunnel)", "tooltip":"From Beginning"},
			{"id":"sub22","task":"Medicham", "spoiler":"(Mt. Pyre)", "tooltip":"From Beginning"},
			{"id":"sub23","task":"Manectric", "spoiler":"(Route 110 - Cycling Road)", "tooltip":"From Beginning"},
			{"id":"sub24","task":"Banette", "spoiler":"(Mt. Pyre)", "tooltip":"From Beginning"},
			{"id":"sub25","task":"Absol", "spoiler":"(Safari Zone)", "tooltip":"From Beginning"},
			{"id":"sub26","task":"Garchomp", "spoiler":"(From Aarune after achieving Platinum Rank)", "tooltip":"From Beginning"},
			{"id":"sub27","task":"Lucario", "spoiler":"(From Lisia after beating all Master Rank Contests and then defeating her)", "tooltip":"From Beginning"},
			{"id":"sub28","task":"Abomasnow", "spoiler":"(Route 123 Berry Garden)", "tooltip":"After Primal Groudon/Kyogre narrative"}
		]
	},
	{"id":"task15",
		"task":"Complete All Trick House Chambers",
		"category":"activities",
		"row": 3,
		"col": 18,
		"subtasks":[
			{"id":"sub1", "task":"Chamber 1 - Cut"},
			{"id":"sub2", "task":"Chamber 2 - Rock Smash"},
			{"id":"sub3", "task":"Chamber 3 - Flash"},
			{"id":"sub4", "task":"Chamber 4 - Strength"},
			{"id":"sub5", "task":"Chamber 5 - None"},
			{"id":"sub6", "task":"Chamber 6 - None"}
		]
	},
	{"id":"task17",
		"task":"Achieve All Ranks in Secret Base Capture the Flag",
		"category":"activities",
		"row": 3,
		"col": 17,
		"subtasks":[
			{"id":"sub1", "task":"Bronze Rank - 30 Flags (Blackboard)"},
			{"id":"sub2", "task":"Silver Rank - 100 Flags (Jukebox)"},
			{"id":"sub3", "task":"Gold Rank - 500 Flags (Mood Lighting)"},
			{"id":"sub4", "task":"Platinum Rank - 1000 Flags (Confetti Ball)"}
		]
	},
	{"id":"task18",
		"task":"Obtain Elegant Items from Glass Workshop",
		"category":"activities",
		"row": 3,
		"col": 17,
		"subtasks":[
			{"id":"sub1", "task":"Elegant Chair"},
			{"id":"sub2", "task":"Elegant Desk"}
		]
	},
	{"id":"task19",
		"task":"Obtain Master Rank from Battle Institute",
		"category":"battle",
		"row": 3,
		"col": 13,
		"splitCol": 2,
		"subtasks":[
			{"id":"sub1", "task":"Beginner Rank"},
			{"id":"sub2", "task":"Novice Rank"},
			{"id":"sub3", "task":"Normal Rank"},
			{"id":"sub4", "task":"Super Rank"},
			{"id":"sub5", "task":"Hyper Rank"},
			{"id":"sub6", "task":"Elite Rank"}
		]
	},
	{"id":"task20",
		"task":"Complete Mr. Bonding Subquest",
		"category":"activities",
		"row": 3,
		"col": 18
	},
	{"id":"task21",
		"task":"Complete Wattson's New Mauville Subquest",
		"category":"activities",
		"row": 3,
		"col": 18
	},
	{"id":"task22",
		"task":"Bonus Story Sequences - Optional & Event",
		"category":"epilogue",
		"formats":[{"word":"Optional", "format":"red"}, {"word":"Event", "format":"seafoam"}],
		"row": 3,
		"col": 15,
		"subtasks":[
			{"id":"sub1", "task":"Event Shiny Beldum & Mr. Stone / Steven Stone / Route 114 Fossil Maniac", "formats":[{"word":"Event", "format":"seafoam"}]},
			{"id":"sub2", "task":"Event Diancie & PKMN Center Gentleman", "formats":[{"word":"Event", "format":"seafoam"}]}
		]
	}
]}
